LanusStats/__init__.py
LanusStats/config.py
LanusStats/datafactory.py
LanusStats/exceptions.py
LanusStats/fbref.py
LanusStats/fotmob.py
LanusStats/functions.py
LanusStats/sofascore.py
LanusStats/threesixfivescores.py
LanusStats/transfermarkt.py
LanusStats/visualizations.py
LanusStats/fonts/BungeeInline-Regular.ttf
LanusStats/fonts/Catamaran-ExtraBold.ttf
LanusStats/fonts/Catamaran-Medium.ttf
LanusStats/fonts/FjallaOne-Regular.ttf
LanusStats/fonts/Lato-Bold.ttf
lanusstats-1.9.1.dist-info/METADATA
lanusstats-1.9.1.dist-info/WHEEL
lanusstats-1.9.1.dist-info/top_level.txt
lanusstats-1.9.1.dist-info/RECORD
