Metadata-Version: 2.1
Name: lanusstats
Version: 1.9.1
Summary: Python library for scraping football data and visualize it / Libreria de Python para scrapear data de fútbol y visualizarla
Home-page: https://github.com/federicorabanos
Author: Federico Rábanos
Author-email: lanusstats@gmail.com
License: MIT
Requires-Dist: pandas
Requires-Dist: mplsoccer
Requires-Dist: requests
Requires-Dist: matplotlib
Requires-Dist: numpy
Requires-Dist: bs4
Requires-Dist: Pillow
Requires-Dist: faker
Requires-Dist: undetected-chromedriver
